PriceHero/__init__.py
PriceHero/_acer.py
PriceHero/_adafruit.py
PriceHero/_adidas.py
PriceHero/_amazon.py
PriceHero/_ann_taylor.py
PriceHero/_bestbuy.py
PriceHero/_boohoo.py
PriceHero/_chess_shop.py
PriceHero/_dell.py
PriceHero/_etsy.py
PriceHero/_github_shop.py
PriceHero/_gucci.py
PriceHero/_joann.py
PriceHero/_journeys.py
PriceHero/_jumia.py
PriceHero/_konga.py
PriceHero/_lids.py
PriceHero/_louis_vuitton.py
PriceHero/_michaels.py
PriceHero/_minecraft_shop.py
PriceHero/_newegg.py
PriceHero/_overstock.py
PriceHero/_pishop.py
PriceHero/_tjmaxx.py
PriceHero/_walgreens.py
PriceHero/_walmart.py
PriceHero/_whbm.py
PriceHero/_xbox.py
PriceHero_mehtaarn000-0.5.9.dist-info/LICENSE
PriceHero_mehtaarn000-0.5.9.dist-info/METADATA
PriceHero_mehtaarn000-0.5.9.dist-info/WHEEL
PriceHero_mehtaarn000-0.5.9.dist-info/top_level.txt
PriceHero_mehtaarn000-0.5.9.dist-info/RECORD
