Metadata-Version: 2.1
Name: PriceHero-mehtaarn000
Version: 0.5.9
Summary: A python module that will allow users to get product prices information from a multitude of different websites. 
Home-page: https://github.com/mehtaarn000/PriceHero
Author: mehtaarn000
License: UNKNOWN
Platform: UNKNOWN
Classifier: Programming Language :: Python :: 3
Classifier: License :: OSI Approved :: MIT License
Classifier: Operating System :: OS Independent
Requires-Python: >=3.6
